AnnoSINE/AnnoSINE_v2.py
AnnoSINE/AnnoSINE_v2_old.py
AnnoSINE/SINEFinder.py
AnnoSINE/TSD_Searcher_multi.js
AnnoSINE/__init__.py
AnnoSINE/paf2blast6_chunking2_parallel3_ordered_parts.py
AnnoSINE/paf2blast6_chunking2_parallel3_ordered_parts_old.py
AnnoSINE/Dfam_hmm/DF0000001_MIR/DF0000001_MIR.hmm
AnnoSINE/Dfam_hmm/DF0000007_AluJb/DF0000007_AluJb.hmm
AnnoSINE/Dfam_hmm/DF0000034_AluJo/DF0000034_AluJo.hmm
AnnoSINE/Dfam_hmm/DF0000039_AluSg/DF0000039_AluSg.hmm
AnnoSINE/Dfam_hmm/DF0000051_AluSz/DF0000051_AluSz.hmm
AnnoSINE/Dfam_hmm/DF0000067_AmnSINE1/DF0000067_AmnSINE1.hmm
AnnoSINE/Dfam_hmm/DF0000068_AmnSINE2/DF0000068_AmnSINE2.hmm
AnnoSINE/Dfam_hmm/DF0000073_BC200/DF0000073_BC200.hmm
AnnoSINE/Dfam_hmm/DF0000142_FAM/DF0000142_FAM.hmm
AnnoSINE/Dfam_hmm/DF0000143_FLAM_A/DF0000143_FLAM_A.hmm
AnnoSINE/Dfam_hmm/DF0000144_FLAM_C/DF0000144_FLAM_C.hmm
AnnoSINE/Dfam_hmm/DF0000147_FRAM/DF0000147_FRAM.hmm
AnnoSINE/Dfam_hmm/DF0000368_LFSINE_Vert/DF0000368_LFSINE_Vert.hmm
AnnoSINE/Dfam_hmm/DF0000974_MIR3/DF0000974_MIR3.hmm
AnnoSINE/Dfam_hmm/DF0000975_MIRb/DF0000975_MIRb.hmm
AnnoSINE/Dfam_hmm/DF0000976_MIRc/DF0000976_MIRc.hmm
AnnoSINE/Dfam_hmm/DF0000996_MamSINE1/DF0000996_MamSINE1.hmm
AnnoSINE/Dfam_hmm/DF0001253_MIR1_Amn/DF0001253_MIR1_Amn.hmm
AnnoSINE/Dfam_hmm/DF0001353_CELE45/DF0001353_CELE45.hmm
AnnoSINE/Dfam_hmm/DF0001423_LmeSINE1c/DF0001423_LmeSINE1c.hmm
AnnoSINE/Dfam_hmm/DF0001522_SINE1_CE/DF0001522_SINE1_CE.hmm
AnnoSINE/Dfam_hmm/DF0001733_B1_Mm/DF0001733_B1_Mm.hmm
AnnoSINE/Dfam_hmm/DF0001734_B1_Mus1/DF0001734_B1_Mus1.hmm
AnnoSINE/Dfam_hmm/DF0001735_B2_Mm1a/DF0001735_B2_Mm1a.hmm
AnnoSINE/Dfam_hmm/DF0001736_B2_Mm1t/DF0001736_B2_Mm1t.hmm
AnnoSINE/Dfam_hmm/DF0001737_B2_Mm2/DF0001737_B2_Mm2.hmm
AnnoSINE/Dfam_hmm/DF0001738_B3/DF0001738_B3.hmm
AnnoSINE/Dfam_hmm/DF0001739_B3A/DF0001739_B3A.hmm
AnnoSINE/Dfam_hmm/DF0001740_B4/DF0001740_B4.hmm
AnnoSINE/Dfam_hmm/DF0001741_BC1_Mm/DF0001741_BC1_Mm.hmm
AnnoSINE/Dfam_hmm/DF0001792_ID_B1/DF0001792_ID_B1.hmm
annosine2-2.0.9.dist-info/LICENSE
annosine2-2.0.9.dist-info/METADATA
annosine2-2.0.9.dist-info/WHEEL
annosine2-2.0.9.dist-info/entry_points.txt
annosine2-2.0.9.dist-info/top_level.txt
annosine2-2.0.9.dist-info/zip-safe
annosine2-2.0.9.dist-info/RECORD
