Metadata-Version: 2.1
Name: annosine2
Version: 2.0.9
Summary: AnnoSINE_v2 - SINE Annotation Tool for Plant and Animal Genomes
Home-page: https://github.com/liaoherui/AnnoSINE_v2
Author: Herui Liao, Shujun Ou, and Yang Li
Author-email: heruiliao2-c@my.cityu.edu.hk
License-File: LICENSE
Requires-Dist: cycler
Requires-Dist: kiwisolver
Requires-Dist: matplotlib
Requires-Dist: numpy
Requires-Dist: Pillow
Requires-Dist: pyparsing
Requires-Dist: python-dateutil
Requires-Dist: six
